LICENSE
MANIFEST.in
README.rst
requirements.txt
setup.py
typingdict/__init__.py
typingdict/__main__.py
typingdict/beautifier.py
typingdict/typer.py
typingdict.egg-info/PKG-INFO
typingdict.egg-info/SOURCES.txt
typingdict.egg-info/dependency_links.txt
typingdict.egg-info/top_level.txt