Metadata-Version: 2.1
Name: typingdict
Version: 0.1.3
Summary: Generate TypedDict Automatically
Home-page: https://github.com/am230/typingdict
Author: am230
License: MIT Licence
Keywords: Automation,Typing
Platform: any
Requires: strinpy
Requires: astor
Requires: click
License-File: LICENSE
